build/lib/build/lib/build/lib/generic_admin_actions/__init__.py
build/lib/build/lib/build/lib/generic_admin_actions/__version__.py
build/lib/build/lib/build/lib/generic_admin_actions/admin.py
build/lib/build/lib/build/lib/generic_admin_actions/apps.py
build/lib/build/lib/build/lib/generic_admin_actions/forms.py
build/lib/build/lib/build/lib/generic_admin_actions/migrations/__init__.py
build/lib/build/lib/build/lib/tests/testapp/__init__.py
build/lib/build/lib/build/lib/tests/testapp/actions.py
build/lib/build/lib/build/lib/tests/testapp/admin.py
build/lib/build/lib/build/lib/tests/testapp/apps.py
build/lib/build/lib/build/lib/tests/testapp/models.py
build/lib/build/lib/build/lib/tests/testapp/settings.py
build/lib/build/lib/build/lib/tests/testapp/urls.py
build/lib/build/lib/build/lib/tests/testapp/wsgi.py
build/lib/build/lib/build/lib/tests/testapp/management/__init__.py
build/lib/build/lib/build/lib/tests/testapp/management/commands/__init__.py
build/lib/build/lib/build/lib/tests/testapp/management/commands/testapp.py
build/lib/build/lib/build/lib/tests/testapp/migrations/0001_initial.py
build/lib/build/lib/build/lib/tests/testapp/migrations/__init__.py
build/lib/build/lib/build/lib/tests/testapp/tests/__init__.py
build/lib/build/lib/build/lib/tests/testapp/tests/test_generic_admin_actions.py
build/lib/build/lib/generic_admin_actions/__init__.py
build/lib/build/lib/generic_admin_actions/__version__.py
build/lib/build/lib/generic_admin_actions/admin.py
build/lib/build/lib/generic_admin_actions/apps.py
build/lib/build/lib/generic_admin_actions/forms.py
build/lib/build/lib/generic_admin_actions/migrations/__init__.py
build/lib/build/lib/tests/testapp/__init__.py
build/lib/build/lib/tests/testapp/actions.py
build/lib/build/lib/tests/testapp/admin.py
build/lib/build/lib/tests/testapp/apps.py
build/lib/build/lib/tests/testapp/models.py
build/lib/build/lib/tests/testapp/settings.py
build/lib/build/lib/tests/testapp/urls.py
build/lib/build/lib/tests/testapp/wsgi.py
django_generic_admin_actions-0.4.dist-info/licenses/LICENCE
django_generic_admin_actions-0.4.dist-info/METADATA
django_generic_admin_actions-0.4.dist-info/WHEEL
django_generic_admin_actions-0.4.dist-info/top_level.txt
django_generic_admin_actions-0.4.dist-info/zip-safe
django_generic_admin_actions-0.4.dist-info/RECORD
